poequora/__init__.py
poequora/api.py
poequora/mail.py
poequora/graphql/__init__.py
poequora-1.0.1.dist-info/METADATA
poequora-1.0.1.dist-info/WHEEL
poequora-1.0.1.dist-info/top_level.txt
poequora-1.0.1.dist-info/RECORD
