Metadata-Version: 2.1
Name: poequora
Version: 1.0.1
Summary: poe
Home-page: https://pypi.org/project/poequora/
Author: xtekky
Author-email: 
Project-URL: Bug Tracker, https://pypi.org/project/poequora/
Classifier: Programming Language :: Python :: 3
Classifier: License :: OSI Approved :: MIT License
Classifier: Operating System :: OS Independent
Requires-Python: >=3.6
Requires-Dist: pypasser
Requires-Dist: fake-useragent
Requires-Dist: websocket-client
Requires-Dist: tls-client
Requires-Dist: pydantic
Requires-Dist: selenium
